disable_gc.py
disable_gc-0.1.0.dist-info/LICENSE
disable_gc-0.1.0.dist-info/METADATA
disable_gc-0.1.0.dist-info/WHEEL
disable_gc-0.1.0.dist-info/top_level.txt
disable_gc-0.1.0.dist-info/RECORD
